{
    "key": "group_5cecea6b0e431",
    "title": "Page Builder",
    "fields": [
        {
            "key": "field_5cecea74b1e09",
            "label": "Sections",
            "name": "sections",
            "type": "flexible_content",
            "instructions": "",
            "required": 0,
            "conditional_logic": 0,
            "wrapper": {
                "width": "",
                "class": "",
                "id": ""
            },
            "layouts": {
                "layout_5ec00f1a57cb2": {
                    "key": "layout_5ec00f1a57cb2",
                    "name": "hero_section",
                    "label": "Hero Section",
                    "display": "block",
                    "sub_fields": [
                        {
                            "key": "field_5ec00f4a57cb3",
                            "label": "Logo",
                            "name": "hs_logo",
                            "type": "image",
                            "instructions": "",
                            "required": 0,
                            "conditional_logic": 0,
                            "wrapper": {
                                "width": "50",
                                "class": "",
                                "id": ""
                            },
                            "return_format": "array",
                            "preview_size": "medium",
                            "library": "all",
                            "min_width": "",
                            "min_height": "",
                            "min_size": "",
                            "max_width": "",
                            "max_height": "",
                            "max_size": "",
                            "mime_types": ""
                        },
                        {
                            "key": "field_5ec00fdd57cb6",
                            "label": "Video Image",
                            "name": "hs_video_image",
                            "type": "image",
                            "instructions": "",
                            "required": 0,
                            "conditional_logic": 0,
                            "wrapper": {
                                "width": "50",
                                "class": "",
                                "id": ""
                            },
                            "return_format": "array",
                            "preview_size": "medium",
                            "library": "all",
                            "min_width": "",
                            "min_height": "",
                            "min_size": "",
                            "max_width": "",
                            "max_height": "",
                            "max_size": "",
                            "mime_types": ""
                        },
                        {
                            "key": "field_5ec5b89787132",
                            "label": "Copy",
                            "name": "hs_copy",
                            "type": "wysiwyg",
                            "instructions": "",
                            "required": 0,
                            "conditional_logic": 0,
                            "wrapper": {
                                "width": "",
                                "class": "",
                                "id": ""
                            },
                            "default_value": "",
                            "tabs": "all",
                            "toolbar": "full",
                            "media_upload": 1,
                            "delay": 0
                        },
                        {
                            "key": "field_5ec0106657cb7",
                            "label": "CTAs",
                            "name": "hs_ctas",
                            "type": "repeater",
                            "instructions": "",
                            "required": 0,
                            "conditional_logic": 0,
                            "wrapper": {
                                "width": "100",
                                "class": "",
                                "id": ""
                            },
                            "collapsed": "",
                            "min": 0,
                            "max": 0,
                            "layout": "table",
                            "button_label": "Add CTA",
                            "sub_fields": [
                                {
                                    "key": "field_5ec0107057cb8",
                                    "label": "CTA",
                                    "name": "hs_cta",
                                    "type": "link",
                                    "instructions": "",
                                    "required": 0,
                                    "conditional_logic": 0,
                                    "wrapper": {
                                        "width": "",
                                        "class": "",
                                        "id": ""
                                    },
                                    "return_format": "array"
                                }
                            ]
                        },
                        {
                            "key": "field_5ec599fd2d11e",
                            "label": "Video Provider",
                            "name": "hs_video_provider",
                            "type": "select",
                            "instructions": "",
                            "required": 0,
                            "conditional_logic": 0,
                            "wrapper": {
                                "width": "50",
                                "class": "",
                                "id": ""
                            },
                            "choices": {
                                "youtube": "YouTube",
                                "vimeo": "Vimeo"
                            },
                            "default_value": [],
                            "allow_null": 0,
                            "multiple": 0,
                            "ui": 0,
                            "return_format": "value",
                            "ajax": 0,
                            "placeholder": ""
                        },
                        {
                            "key": "field_5ec59a1d2d11f",
                            "label": "Video ID",
                            "name": "hs_video_id",
                            "type": "text",
                            "instructions": "",
                            "required": 0,
                            "conditional_logic": 0,
                            "wrapper": {
                                "width": "50",
                                "class": "",
                                "id": ""
                            },
                            "default_value": "",
                            "placeholder": "",
                            "prepend": "",
                            "append": "",
                            "maxlength": ""
                        },
                        {
                            "key": "field_5ec13a61a9e5f",
                            "label": "Section ID",
                            "name": "hs_section_id",
                            "type": "text",
                            "instructions": "",
                            "required": 0,
                            "conditional_logic": 0,
                            "wrapper": {
                                "width": "",
                                "class": "",
                                "id": ""
                            },
                            "default_value": "",
                            "placeholder": "",
                            "prepend": "",
                            "append": "",
                            "maxlength": ""
                        }
                    ],
                    "min": "",
                    "max": ""
                }
            },
            "button_label": "Add Section",
            "min": "",
            "max": ""
        }
    ],
    "location": [
        [
            {
                "param": "post_type",
                "operator": "==",
                "value": "page"
            }
        ]
    ],
    "menu_order": 0,
    "position": "normal",
    "style": "default",
    "label_placement": "top",
    "instruction_placement": "label",
    "hide_on_screen": "",
    "active": 1,
    "description": "",
    "modified": 1590016254
}